mastodon_to_bluesky/__init__.py
mastodon_to_bluesky/__main__.py
mastodon_to_bluesky/bluesky.py
mastodon_to_bluesky/cli.py
mastodon_to_bluesky/interactive.py
mastodon_to_bluesky/mastodon.py
mastodon_to_bluesky/models.py
mastodon_to_bluesky/transfer.py
mastodon_to_bluesky-1.0.0.dist-info/METADATA
mastodon_to_bluesky-1.0.0.dist-info/WHEEL
mastodon_to_bluesky-1.0.0.dist-info/entry_points.txt
mastodon_to_bluesky-1.0.0.dist-info/licenses/LICENSE
mastodon_to_bluesky-1.0.0.dist-info/RECORD
