Metadata-Version: 2.4
Name: mastodon-to-bluesky
Version: 1.0.0
Summary: Transfer posts from Mastodon to Bluesky
Project-URL: Homepage, https://github.com/jonatkinson/mastodon-to-bluesky
Project-URL: Bug Reports, https://github.com/jonatkinson/mastodon-to-bluesky/issues
Project-URL: Source, https://github.com/jonatkinson/mastodon-to-bluesky
Author-email: Jon Atkinson <jon@jonatkinson.co.uk>
License: MIT
License-File: LICENSE
Keywords: atproto,bluesky,fediverse,mastodon,migration,social-media
Classifier: Development Status :: 4 - Beta
Classifier: Environment :: Console
Classifier: Intended Audience :: End Users/Desktop
Classifier: License :: OSI Approved :: MIT License
Classifier: Operating System :: OS Independent
Classifier: Programming Language :: Python :: 3
Classifier: Programming Language :: Python :: 3.11
Classifier: Programming Language :: Python :: 3.12
Classifier: Programming Language :: Python :: 3.13
Classifier: Topic :: Communications :: Chat
Classifier: Topic :: Internet
Classifier: Topic :: Utilities
Requires-Python: >=3.11
Requires-Dist: beautifulsoup4>=4.12.0
Requires-Dist: click>=8.1.0
Requires-Dist: httpx>=0.27.0
Requires-Dist: pydantic>=2.0.0
Requires-Dist: python-dateutil>=2.8.0
Requires-Dist: rich>=13.0.0
